pelican/plugins/readtime/__init__.py
pelican/plugins/readtime/readtime.py
pelican/plugins/readtime/test_readtime.py
pelican_readtime-0.2.1.dist-info/LICENSE
pelican_readtime-0.2.1.dist-info/METADATA
pelican_readtime-0.2.1.dist-info/WHEEL
pelican_readtime-0.2.1.dist-info/top_level.txt
pelican_readtime-0.2.1.dist-info/zip-safe
pelican_readtime-0.2.1.dist-info/RECORD
