Metadata-Version: 2.1
Name: pelican-readtime
Version: 0.2.1
Summary: Plugin for Pelican that computes average read time.
Home-page: https://github.com/JenkinsDev/pelican-readtime
Download-URL: https://github.com/JenkinsDev/pelican-readtime
Author: David Jenkins, Deepak Bhalla, Jonathan Dektiar
Author-email: djenkinsdev@gmail.com, contact@deepakrb.com, contact@jonathandekhtiar.eu
Maintainer: David Jenkins, Deepak Bhalla, Jonathan Dektiar
Maintainer-email: djenkinsdev@gmail.com, contact@deepakrb.com, contact@jonathandekhtiar.eu
License: MIT
Keywords: pelican blogging blog static webdevelopment plugin pelican-plugin readtime python python3 python2
Classifier: Development Status :: 5 - Production/Stable
Classifier: Natural Language :: English
Classifier: License :: OSI Approved :: MIT License
Classifier: Operating System :: OS Independent
Classifier: Programming Language :: Python
Classifier: Programming Language :: Python :: 3
Classifier: Programming Language :: Python :: 3.4
Classifier: Programming Language :: Python :: 3.5
Classifier: Programming Language :: Python :: 3.6
Classifier: Programming Language :: Python :: 3.7
Classifier: Topic :: Software Development :: Libraries :: Python Modules
License-File: LICENSE
Requires-Dist: pelican>=3.6
